README.md
setup.py
binary_B64_encoder/__init__.py
binary_B64_encoder/b64encode.py
binary_B64_encoder.egg-info/PKG-INFO
binary_B64_encoder.egg-info/SOURCES.txt
binary_B64_encoder.egg-info/dependency_links.txt
binary_B64_encoder.egg-info/entry_points.txt
binary_B64_encoder.egg-info/requires.txt
binary_B64_encoder.egg-info/top_level.txt