Metadata-Version: 2.1
Name: binary-B64-encoder
Version: 1.0.8
Summary: This script encode the binary input file to base64
Home-page: https://github.com/gerardogu/binary-B64-encoder
Author: Gerardo G. Urtiaga 
Author-email: gerardo.garcia.urtiaga@gmail.com
License: MIT License
